django_watchlog_apm/__init__.py
django_watchlog_apm/collector.py
django_watchlog_apm/error_handler.py
django_watchlog_apm/middleware.py
django_watchlog_apm/sender.py
django_watchlog_apm-0.1.3.dist-info/licenses/LICENSE
django_watchlog_apm-0.1.3.dist-info/METADATA
django_watchlog_apm-0.1.3.dist-info/WHEEL
django_watchlog_apm-0.1.3.dist-info/top_level.txt
django_watchlog_apm-0.1.3.dist-info/RECORD
