Metadata-Version: 2.4
Name: django_watchlog_apm
Version: 0.1.3
Summary: Watchlog APM integration for Django
Author: Mohammadreza
License: MIT
Project-URL: Watchlog, https://watchlog.io
Project-URL: Source, https://github.com/watchlogserver/django_watchlog_apm.git
Classifier: Framework :: Django
Classifier: Programming Language :: Python :: 3
Classifier: License :: OSI Approved :: MIT License
Classifier: Operating System :: OS Independent
Classifier: Topic :: Software Development :: Libraries :: Application Frameworks
Requires-Python: >=3.7
License-File: LICENSE
Dynamic: author
Dynamic: classifier
Dynamic: description
Dynamic: description-content-type
Dynamic: license
Dynamic: license-file
Dynamic: project-url
Dynamic: requires-python
Dynamic: summary
